<?xml version='1.0' encoding='utf8'?>
<nuitka-compilation-report nuitka_version="2.8.10" nuitka_commercial_version="not installed" mode="standalone" completion="exception">
  <exception exception_type="UnicodeDecodeError" exception_value="'utf-8' codec can't decode byte 0xb1 in position 49928: invalid start byte">
Traceback (most recent call last):
  File "/home/altimate/Coding/0/electron-python-app/.venv/lib/python3.12/site-packages/nuitka/MainControl.py", line 1214, in main
    _main()
  File "/home/altimate/Coding/0/electron-python-app/.venv/lib/python3.12/site-packages/nuitka/MainControl.py", line 1033, in _main
    main_module = _createMainModule()
                  ^^^^^^^^^^^^^^^^^^^
  File "/home/altimate/Coding/0/electron-python-app/.venv/lib/python3.12/site-packages/nuitka/MainControl.py", line 229, in _createMainModule
    scanIncludedPackage(package_name)
  File "/home/altimate/Coding/0/electron-python-app/.venv/lib/python3.12/site-packages/nuitka/importing/Recursion.py", line 592, in scanIncludedPackage
    scanPluginPath(
  File "/home/altimate/Coding/0/electron-python-app/.venv/lib/python3.12/site-packages/nuitka/importing/Recursion.py", line 445, in scanPluginPath
    scanPluginSinglePath(
  File "/home/altimate/Coding/0/electron-python-app/.venv/lib/python3.12/site-packages/nuitka/importing/Recursion.py", line 424, in scanPluginSinglePath
    _addIncludedModule(module=module, package_only=package_only)
  File "/home/altimate/Coding/0/electron-python-app/.venv/lib/python3.12/site-packages/nuitka/importing/Recursion.py", line 344, in _addIncludedModule
    scanPluginSinglePath(
  File "/home/altimate/Coding/0/electron-python-app/.venv/lib/python3.12/site-packages/nuitka/importing/Recursion.py", line 424, in scanPluginSinglePath
    _addIncludedModule(module=module, package_only=package_only)
  File "/home/altimate/Coding/0/electron-python-app/.venv/lib/python3.12/site-packages/nuitka/importing/Recursion.py", line 354, in _addIncludedModule
    scanPluginSinglePath(
  File "/home/altimate/Coding/0/electron-python-app/.venv/lib/python3.12/site-packages/nuitka/importing/Recursion.py", line 405, in scanPluginSinglePath
    decision, decision_reason = decideRecursion(
                                ^^^^^^^^^^^^^^^^
  File "/home/altimate/Coding/0/electron-python-app/.venv/lib/python3.12/site-packages/nuitka/importing/Recursion.py", line 143, in decideRecursion
    Plugins.onModuleUsageLookAhead(
  File "/home/altimate/Coding/0/electron-python-app/.venv/lib/python3.12/site-packages/nuitka/plugins/Plugins.py", line 1140, in onModuleUsageLookAhead
    plugin.onModuleUsageLookAhead(
  File "/home/altimate/Coding/0/electron-python-app/.venv/lib/python3.12/site-packages/nuitka/plugins/standard/ImplicitImports.py", line 784, in onModuleUsageLookAhead
    if get_module_source() is None:
       ^^^^^^^^^^^^^^^^^^^
  File "/home/altimate/Coding/0/electron-python-app/.venv/lib/python3.12/site-packages/nuitka/plugins/Plugins.py", line 1129, in getModuleSourceCode
    return readSourceCodeFromFilename(
           ^^^^^^^^^^^^^^^^^^^^^^^^^^^
  File "/home/altimate/Coding/0/electron-python-app/.venv/lib/python3.12/site-packages/nuitka/tree/SourceHandling.py", line 213, in readSourceCodeFromFilename
    return readSourceCodeFromFilenameWithInformation(
           ^^^^^^^^^^^^^^^^^^^^^^^^^^^^^^^^^^^^^^^^^^
  File "/home/altimate/Coding/0/electron-python-app/.venv/lib/python3.12/site-packages/nuitka/tree/SourceHandling.py", line 178, in readSourceCodeFromFilenameWithInformation
    source_code = _readSourceCodeFromFilename3(source_filename)
                  ^^^^^^^^^^^^^^^^^^^^^^^^^^^^^^^^^^^^^^^^^^^^^
  File "/home/altimate/Coding/0/electron-python-app/.venv/lib/python3.12/site-packages/nuitka/tree/SourceHandling.py", line 71, in _readSourceCodeFromFilename3
    return source_file.read()
           ^^^^^^^^^^^^^^^^^^
  File "/usr/lib/python3.12/codecs.py", line 322, in decode
    (result, consumed) = self._buffer_decode(data, self.errors, final)
                         ^^^^^^^^^^^^^^^^^^^^^^^^^^^^^^^^^^^^^^^^^^^^^
UnicodeDecodeError: 'utf-8' codec can't decode byte 0xb1 in position 49928: invalid start byte
</exception>
  <performance>
    <memory_usage name="after_launch" value="51490816" />
  </performance>
  <data_file name="nodriver/cdp/README.md" source="${sys.prefix}/lib/python3.12/site-packages/nodriver/cdp/README.md" size="172" reason="package 'nodriver' package data" tags="user,package_data,copy" />
  <data_composer blob_size="None" />
  <command_line>
    <option value="--standalone" />
    <option value="--follow-imports" />
    <option value="--include-package=nodriver" />
    <option value="--include-package=nodriver.cdp" />
    <option value="--include-package-data=nodriver" />
    <option value="--include-package=scripts" />
    <option value="--output-dir=../build/nuitka_build" />
    <option value="--output-filename=excec_worker" />
    <option value="--assume-yes-for-downloads" />
    <option value="scripts/core/build_launcher.py" />
  </command_line>
  <plugins>
    <plugin name="anti-bloat" user_enabled="no" />
    <plugin name="data-files" user_enabled="no" />
    <plugin name="delvewheel" user_enabled="no" />
    <plugin name="dll-files" user_enabled="no" />
    <plugin name="eventlet" user_enabled="no" />
    <plugin name="gevent" user_enabled="no" />
    <plugin name="gi" user_enabled="no" />
    <plugin name="glfw" user_enabled="no" />
    <plugin name="implicit-imports" user_enabled="no" />
    <plugin name="kivy" user_enabled="no" />
    <plugin name="matplotlib" user_enabled="no" />
    <plugin name="multiprocessing" user_enabled="no" />
    <plugin name="options-nanny" user_enabled="no" />
    <plugin name="pbr-compat" user_enabled="no" />
    <plugin name="pkg-resources" user_enabled="no" />
    <plugin name="playwright" user_enabled="no" />
    <plugin name="pywebview" user_enabled="no" />
    <plugin name="spacy" user_enabled="no" />
    <plugin name="transformers" user_enabled="no" />
  </plugins>
  <distributions />
  <python python_exe="${sys.prefix}/bin/python" python_flavor="Debian Python" python_version="3.12.3" os_name="Linux" os_release="Linuxmint-Ubuntu-22" arch_name="x86_64" filesystem_encoding="utf-8">
    <search_path>
      <path value="${cwd}" />
      <path value="${cwd}/scripts/core" />
      <path value="${sys.real_prefix}/lib/python3.12" />
      <path value="${sys.real_prefix}/lib/python3.12/lib-dynload" />
      <path value="${sys.prefix}/lib/python3.12/site-packages" />
      <path value="${sys.prefix}/lib/python3.12/site-packages/setuptools/_vendor" />
    </search_path>
  </python>
  <output run_filename="~/Coding/0/electron-python-app/build/nuitka_build/build_launcher.dist/excec_worker" />
</nuitka-compilation-report>
